RoboticProcessAutomation/__init__.py
RoboticProcessAutomation/env.py
RoboticProcessAutomation/img_recog.py
RoboticProcessAutomation/send_keys.py
RoboticProcessAutomation/trace_log.py
RoboticProcessAutomation-1.0.0.dist-info/LICENSE
RoboticProcessAutomation-1.0.0.dist-info/METADATA
RoboticProcessAutomation-1.0.0.dist-info/WHEEL
RoboticProcessAutomation-1.0.0.dist-info/top_level.txt
RoboticProcessAutomation-1.0.0.dist-info/RECORD
