Metadata-Version: 2.1
Name: RoboticProcessAutomation
Version: 1.0.0
Summary: Robotic Process Automation Python Package
Home-page: https://github.com/bartmazur90/RoboticProcessAutomation
Author: Bartosz Mazur
Author-email: bartmazur90@gmail.com
License: UNKNOWN
Keywords: python,RPA,Robotic,Process,Automation,Image Recognition
Platform: UNKNOWN
Classifier: Programming Language :: Python :: 3
Classifier: Intended Audience :: Developers
Classifier: Operating System :: OS Independent
Requires-Dist: pillow
Requires-Dist: opencv-python
Requires-Dist: pyautogui
Requires-Dist: pyscreeze
